simple_test_process/__init__.py
simple_test_process/__main__.py
simple_test_process/_vendor/LICENSE.txt
simple_test_process/_vendor/__init__.py
simple_test_process/_vendor/ordered_set-3.1.1.dist-info/INSTALLER
simple_test_process/_vendor/ordered_set-3.1.1.dist-info/METADATA
simple_test_process/_vendor/ordered_set-3.1.1.dist-info/MIT-LICENSE
simple_test_process/_vendor/ordered_set-3.1.1.dist-info/RECORD
simple_test_process/_vendor/ordered_set-3.1.1.dist-info/WHEEL
simple_test_process/_vendor/ordered_set-3.1.1.dist-info/top_level.txt
simple_test_process/_vendor/ordered_set.py
simple_test_process/_vendor/po/__init__.py
simple_test_process/_vendor/po/case_conversion/__init__.py
simple_test_process/_vendor/po/case_conversion/case_conversion.py
simple_test_process/_vendor/po/case_conversion/case_parse.py
simple_test_process/_vendor/po.case_conversion-0.2.0.dist-info/INSTALLER
simple_test_process/_vendor/po.case_conversion-0.2.0.dist-info/LICENSE.txt
simple_test_process/_vendor/po.case_conversion-0.2.0.dist-info/METADATA
simple_test_process/_vendor/po.case_conversion-0.2.0.dist-info/RECORD
simple_test_process/_vendor/po.case_conversion-0.2.0.dist-info/WHEEL
simple_test_process/_vendor/simple_test_default_reporter/__init__.py
simple_test_process/_vendor/simple_test_default_reporter/_vendor/__init__.py
simple_test_process/_vendor/simple_test_default_reporter/_vendor/ordered_set-3.1.1.dist-info/INSTALLER
simple_test_process/_vendor/simple_test_default_reporter/_vendor/ordered_set-3.1.1.dist-info/METADATA
simple_test_process/_vendor/simple_test_default_reporter/_vendor/ordered_set-3.1.1.dist-info/MIT-LICENSE
simple_test_process/_vendor/simple_test_default_reporter/_vendor/ordered_set-3.1.1.dist-info/RECORD
simple_test_process/_vendor/simple_test_default_reporter/_vendor/ordered_set-3.1.1.dist-info/WHEEL
simple_test_process/_vendor/simple_test_default_reporter/_vendor/ordered_set-3.1.1.dist-info/top_level.txt
simple_test_process/_vendor/simple_test_default_reporter/_vendor/ordered_set.py
simple_test_process/_vendor/simple_test_default_reporter/_vendor/simple_chalk/__init__.py
simple_test_process/_vendor/simple_test_default_reporter/_vendor/simple_chalk/src/Style.py
simple_test_process/_vendor/simple_test_default_reporter/_vendor/simple_chalk/src/__init__.py
simple_test_process/_vendor/simple_test_default_reporter/_vendor/simple_chalk/src/data.py
simple_test_process/_vendor/simple_test_default_reporter/_vendor/simple_chalk/src/makeAChalkClass.py
simple_test_process/_vendor/simple_test_default_reporter/_vendor/simple_chalk/src/makeAChalkInstance.py
simple_test_process/_vendor/simple_test_default_reporter/_vendor/simple_chalk/src/makeChalkHelpers.py
simple_test_process/_vendor/simple_test_default_reporter/_vendor/simple_chalk/src/utils/__init__.py
simple_test_process/_vendor/simple_test_default_reporter/_vendor/simple_chalk/src/utils/append.py
simple_test_process/_vendor/simple_test_default_reporter/_vendor/simple_chalk/src/utils/appendAll.py
simple_test_process/_vendor/simple_test_default_reporter/_vendor/simple_chalk/src/utils/assignMissing.py
simple_test_process/_vendor/simple_test_default_reporter/_vendor/simple_chalk/src/utils/flatten.py
simple_test_process/_vendor/simple_test_default_reporter/_vendor/simple_chalk/src/utils/forEach.py
simple_test_process/_vendor/simple_test_default_reporter/_vendor/simple_chalk-0.1.0.dist-info/INSTALLER
simple_test_process/_vendor/simple_test_default_reporter/_vendor/simple_chalk-0.1.0.dist-info/METADATA
simple_test_process/_vendor/simple_test_default_reporter/_vendor/simple_chalk-0.1.0.dist-info/RECORD
simple_test_process/_vendor/simple_test_default_reporter/_vendor/simple_chalk-0.1.0.dist-info/WHEEL
simple_test_process/_vendor/simple_test_default_reporter/_vendor/simple_chalk-0.1.0.dist-info/top_level.txt
simple_test_process/_vendor/simple_test_default_reporter/_vendor/tedent/_vendor/ordered_set-3.1.1-py3.7.egg-info/PKG-INFO
simple_test_process/_vendor/simple_test_default_reporter/_vendor/tedent/_vendor/ordered_set-3.1.1-py3.7.egg-info/SOURCES.txt
simple_test_process/_vendor/simple_test_default_reporter/_vendor/tedent/_vendor/ordered_set-3.1.1-py3.7.egg-info/dependency_links.txt
simple_test_process/_vendor/simple_test_default_reporter/_vendor/tedent/_vendor/ordered_set-3.1.1-py3.7.egg-info/installed-files.txt
simple_test_process/_vendor/simple_test_default_reporter/_vendor/tedent/_vendor/ordered_set-3.1.1-py3.7.egg-info/top_level.txt
simple_test_process/_vendor/simple_test_default_reporter/_vendor/tedent/_vendor/wrapt-1.11.1.dist-info/INSTALLER
simple_test_process/_vendor/simple_test_default_reporter/_vendor/tedent/_vendor/wrapt-1.11.1.dist-info/LICENSE
simple_test_process/_vendor/simple_test_default_reporter/_vendor/tedent/_vendor/wrapt-1.11.1.dist-info/METADATA
simple_test_process/_vendor/simple_test_default_reporter/_vendor/tedent/_vendor/wrapt-1.11.1.dist-info/RECORD
simple_test_process/_vendor/simple_test_default_reporter/_vendor/tedent/_vendor/wrapt-1.11.1.dist-info/WHEEL
simple_test_process/_vendor/simple_test_default_reporter/_vendor/tedent/_vendor/wrapt-1.11.1.dist-info/top_level.txt
simple_test_process/_vendor/simple_test_default_reporter/_vendor/tedent-0.1.5.dist-info/INSTALLER
simple_test_process/_vendor/simple_test_default_reporter/_vendor/tedent-0.1.5.dist-info/METADATA
simple_test_process/_vendor/simple_test_default_reporter/_vendor/tedent-0.1.5.dist-info/RECORD
simple_test_process/_vendor/simple_test_default_reporter/_vendor/tedent-0.1.5.dist-info/WHEEL
simple_test_process/_vendor/simple_test_default_reporter/_vendor/tedent-0.1.5.dist-info/top_level.txt
simple_test_process/_vendor/simple_test_default_reporter/_vendor/wrapt-1.10.11.dist-info/INSTALLER
simple_test_process/_vendor/simple_test_default_reporter/_vendor/wrapt-1.10.11.dist-info/LICENSE
simple_test_process/_vendor/simple_test_default_reporter/_vendor/wrapt-1.10.11.dist-info/METADATA
simple_test_process/_vendor/simple_test_default_reporter/_vendor/wrapt-1.10.11.dist-info/RECORD
