Metadata-Version: 2.1
Name: simple-test-process
Version: 0.4.5
Summary: The process ran by simple_test to isolate the environment
Home-page: https://github.com/olsonpm/py_simple-test-process
Author: Philip Olson
Author-email: philip.olson@pm.me
Requires-Python: >=3.7,<4.0
Classifier: Programming Language :: Python :: 3
Classifier: Programming Language :: Python :: 3.7
Project-URL: Repository, https://github.com/olsonpm/py_simple-test-process
